pas.plugins.headers-2.0.0-py3.12-nspkg.pth
pas/plugins/headers/__init__.py
pas/plugins/headers/browser.py
pas/plugins/headers/configure.zcml
pas/plugins/headers/exportimport.py
pas/plugins/headers/interfaces.py
pas/plugins/headers/parsers.py
pas/plugins/headers/plugins.py
pas/plugins/headers/setuphandlers.py
pas/plugins/headers/testing.py
pas/plugins/headers/utils.py
pas/plugins/headers/locales/pas.plugins.headers.pot
pas/plugins/headers/locales/update.sh
pas/plugins/headers/profiles/default/metadata.xml
pas/plugins/headers/profiles/uninstall/metadata.xml
pas/plugins/headers/tests/__init__.py
pas/plugins/headers/tests/configure.zcml
pas/plugins/headers/tests/test_auth_ticket.py
pas/plugins/headers/tests/test_exportimport.py
pas/plugins/headers/tests/test_functional.py
pas/plugins/headers/tests/test_headerlogin.py
pas/plugins/headers/tests/test_parsers.py
pas/plugins/headers/tests/test_plugins.py
pas/plugins/headers/tests/test_setup.py
pas/plugins/headers/tests/test_utils.py
pas/plugins/headers/tests/profile/pas.plugins.headers.json
pas_plugins_headers-2.0.0.dist-info/LICENSE.GPL
pas_plugins_headers-2.0.0.dist-info/LICENSE.rst
pas_plugins_headers-2.0.0.dist-info/METADATA
pas_plugins_headers-2.0.0.dist-info/WHEEL
pas_plugins_headers-2.0.0.dist-info/entry_points.txt
pas_plugins_headers-2.0.0.dist-info/namespace_packages.txt
pas_plugins_headers-2.0.0.dist-info/top_level.txt
pas_plugins_headers-2.0.0.dist-info/RECORD
