Metadata-Version: 2.2
Name: pas.plugins.headers
Version: 2.0.0
Summary: PAS plugin for authentication based on request headers
Home-page: https://github.com/collective/pas.plugins.headers
Author: Maurits van Rees
Author-email: m.van.rees@zestsoftware.nl
License: GPL version 2
Keywords: Plone,Zope,PAS,acl_users,SAML,Shibboleth
Classifier: Development Status :: 5 - Production/Stable
Classifier: Environment :: Web Environment
Classifier: Framework :: Plone
Classifier: Framework :: Plone :: Addon
Classifier: Framework :: Plone :: 6.0
Classifier: Framework :: Plone :: 6.1
Classifier: Framework :: Plone :: 6.2
Classifier: Programming Language :: Python
Classifier: Programming Language :: Python :: 3.9
Classifier: Programming Language :: Python :: 3.10
Classifier: Programming Language :: Python :: 3.11
Classifier: Programming Language :: Python :: 3.12
Classifier: Programming Language :: Python :: 3.13
Classifier: Operating System :: OS Independent
Classifier: License :: OSI Approved :: GNU General Public License v2 (GPLv2)
Requires-Python: >=3.9
License-File: LICENSE.GPL
License-File: LICENSE.rst
Requires-Dist: AccessControl
Requires-Dist: plone.base
Requires-Dist: Products.GenericSetup
Requires-Dist: Products.PluggableAuthService
Requires-Dist: zExceptions
Requires-Dist: Zope
Provides-Extra: test
Requires-Dist: plone.app.testing; extra == "test"
Requires-Dist: plone.testing; extra == "test"
Dynamic: author
Dynamic: author-email
Dynamic: classifier
Dynamic: description
Dynamic: home-page
Dynamic: keywords
Dynamic: license
Dynamic: provides-extra
Dynamic: requires-dist
Dynamic: requires-python
Dynamic: summary
